{"name":"Most-popular-stories---compatibility-version","tagline":"Android Application. Extracts the most shared and most read stories from popular news websites. So far most of the implementation is in place for the BBC News section. Still in progress. IMPORTANT: requires having android-support-v7-appcompat library project in the same parent folder/workspace as this project. More information at http://developer.android.com/tools/support-library/setup.html. Otherwise use the higher-API version (to be added to my account shortly)","body":"Most-Popular-Stories---Compatibility-version\r\n============================================\r\n\r\nAndroid Application. Extracts the most shared and most read stories from popular news websites. \r\nSo far most of the implementation is in place for the BBC News section. Still in progress. \r\n\r\n***IMPORTANT: requires having android-support-v7-appcompat library project in the same parent folder/workspace as this project.\r\nMore information at http://developer.android.com/tools/support-library/setup.html.\r\nOtherwise use the higher-API version (to be added to my account shortly)***\r\n\r\nKnown Bug: If there is no internet connection on device, the app will crash. This will be fixed. \r\nAlso, the consistency between activity UIs needs to be improved, preferably by having more functionality in the  base activity than presently.\r\n","google":"","note":"Don't delete this file! It's used internally to help with page regeneration."}